litellm_proxy_extras/__init__.py
litellm_proxy_extras/_logging.py
litellm_proxy_extras/migrations/20250326162113_baseline/migration.sql
litellm_proxy_extras/migrations/20250326171002_add_daily_user_table/migration.sql
litellm_proxy_extras/migrations/20250327180120_add_api_requests_to_daily_user_table/migration.sql
litellm_proxy_extras/migrations/20250329084805_new_cron_job_table/migration.sql
litellm_proxy_extras/migrations/20250331215456_track_success_and_failed_requests_daily_agg_table/migration.sql
litellm_proxy_extras/migrations/20250411215431_add_managed_file_table/migration.sql
litellm_proxy_extras/migrations/20250412081753_team_member_permissions/migration.sql
litellm_proxy_extras/migrations/20250415151647_add_cache_read_write_tokens_daily_spend_transactions/migration.sql
litellm_proxy_extras/migrations/20250415191926_add_daily_team_table/migration.sql
litellm_proxy_extras/migrations/20250416115320_add_tag_table_to_db/migration.sql
litellm_proxy_extras/migrations/20250416151339_drop_tag_uniqueness_requirement/migration.sql
litellm_proxy_extras/migrations/20250416185146_add_allowed_routes_litellm_verification_token/migration.sql
litellm_proxy_extras/migrations/20250425182129_add_session_id/migration.sql
litellm_proxy_extras/migrations/20250430193429_add_managed_vector_stores/migration.sql
litellm_proxy_extras/migrations/20250507161526_add_mcp_table_to_db/migration.sql
litellm_proxy_extras/migrations/20250507161527_add_health_check_fields_to_mcp_servers/migration.sql
litellm_proxy_extras/migrations/20250507184818_add_mcp_key_team_permission_mgmt/migration.sql
litellm_proxy_extras/migrations/20250508072103_add_status_to_spendlogs/migration.sql
litellm_proxy_extras/migrations/20250509141545_use_big_int_for_daily_spend_tables/migration.sql
litellm_proxy_extras/migrations/20250510142544_add_session_id_index_spend_logs/migration.sql
litellm_proxy_extras/migrations/20250514142245_add_guardrails_table/migration.sql
litellm_proxy_extras-0.4.29.dist-info/METADATA
litellm_proxy_extras-0.4.29.dist-info/WHEEL
litellm_proxy_extras-0.4.29.dist-info/licenses/LICENSE
litellm_proxy_extras-0.4.29.dist-info/RECORD
